rpy2/interactive/__init__.py
rpy2/interactive/packages.py
rpy2/interactive/process_revents.py
rpy2/ipython/__init__.py
rpy2/ipython/ggplot.py
rpy2/ipython/html.py
rpy2/ipython/rmagic.py
rpy2/ipython/tests/__init__.py
rpy2/ipython/tests/test_ggplot.py
rpy2/ipython/tests/test_html.py
rpy2/ipython/tests/test_rmagic.py
rpy2/robjects/__init__.py
rpy2/robjects/constants.py
rpy2/robjects/conversion.py
rpy2/robjects/environments.py
rpy2/robjects/functions.py
rpy2/robjects/help.py
rpy2/robjects/language.py
rpy2/robjects/methods.py
rpy2/robjects/numpy2ri.py
rpy2/robjects/packages.py
rpy2/robjects/packages_utils.py
rpy2/robjects/pandas2ri.py
rpy2/robjects/robject.py
rpy2/robjects/vectors.py
rpy2/robjects/version.py
rpy2/robjects/lib/__init__.py
rpy2/robjects/lib/dbplyr.py
rpy2/robjects/lib/dplyr.py
rpy2/robjects/lib/ggplot2.py
rpy2/robjects/lib/grdevices.py
rpy2/robjects/lib/grid.py
rpy2/robjects/lib/tidyr.py
rpy2/robjects/tests/robjects/__init__.py
rpy2/robjects/tests/robjects/test_array.py
rpy2/robjects/tests/robjects/test_conversion.py
rpy2/robjects/tests/robjects/test_conversion_numpy.py
rpy2/robjects/tests/robjects/test_dataframe.py
rpy2/robjects/tests/robjects/test_environment.py
rpy2/robjects/tests/robjects/test_formula.py
rpy2/robjects/tests/robjects/test_function.py
rpy2/robjects/tests/robjects/test_help.py
rpy2/robjects/tests/robjects/test_language.py
rpy2/robjects/tests/robjects/test_methods.py
rpy2/robjects/tests/robjects/test_packages.py
rpy2/robjects/tests/robjects/test_packages_utils.py
rpy2/robjects/tests/robjects/test_pandas_conversions.py
rpy2/robjects/tests/robjects/test_robjects.py
rpy2/robjects/tests/robjects/test_rs4.py
rpy2/robjects/tests/robjects/test_serialization.py
rpy2/robjects/tests/robjects/test_translated_function.py
rpy2/robjects/tests/robjects/test_vector.py
rpy2/robjects/tests/robjects/test_vector_datetime.py
rpy2/robjects/tests/robjects/test_vector_extractdelegator.py
rpy2/robjects/tests/robjects/test_vector_factor.py
rpy2_robjects-3.6.2.dist-info/METADATA
rpy2_robjects-3.6.2.dist-info/WHEEL
rpy2_robjects-3.6.2.dist-info/top_level.txt
rpy2_robjects-3.6.2.dist-info/RECORD
